LICENSE
MANIFEST.in
README.md
setup.cfg
setup.py
versioneer.py
pygran_analysis/__init__.py
pygran_analysis/_version.py
pygran_analysis/contacts.py
pygran_analysis/core.py
pygran_analysis/dynamics.py
pygran_analysis/equilibrium.py
pygran_analysis/generator.py
pygran_analysis/imaging.py
pygran_analysis/tools.py
pygran_analysis.egg-info/PKG-INFO
pygran_analysis.egg-info/SOURCES.txt
pygran_analysis.egg-info/dependency_links.txt
pygran_analysis.egg-info/not-zip-safe
pygran_analysis.egg-info/requires.txt
pygran_analysis.egg-info/top_level.txt