Metadata-Version: 2.1
Name: pygran-analysis
Version: 1.1.0
Summary: A package for rapid quantitative analysis of granular/powder systems
Home-page: http://pygran.org
Author: Andrew Abi-Mansour
Author-email: support@pygran.org
License: GNU v2
Keywords: Discrete Element Method,Granular Materials
Platform: UNKNOWN
Classifier: Development Status :: 4 - Beta
Classifier: Topic :: Utilities
Classifier: License :: OSI Approved :: GNU General Public License v2 (GPLv2)
Classifier: Programming Language :: Python :: 3.7
Classifier: Programming Language :: Python :: 3.8
Classifier: Programming Language :: Python :: 3.9
Classifier: Operating System :: POSIX :: Linux
Provides-Extra: extras
Provides-Extra: tests
License-File: LICENSE
